image_detection_service/__init__.py
image_detection_service/api_v1/__init__.py
image_detection_service/api_v1/image_detection_service.py
image_detection_service/app.py
image_detection_service/constants.py
image_detection_service/metrics.py
image_detection_service/run.py
image_detection_service/service.py
image_detection_service/utils.py
image_detection_service/version.py
image_detection_service-0.5.0.dist-info/entry_points.txt
image_detection_service-0.5.0.dist-info/LICENSE.txt
image_detection_service-0.5.0.dist-info/WHEEL
image_detection_service-0.5.0.dist-info/METADATA
image_detection_service-0.5.0.dist-info/RECORD
